os_cloud_storage/__init__.py
os_cloud_storage/os_azure.py
os_cloud_storage/os_gcp.py
os_cloud_storage/os_s3.py
os_py_lib_cloud-1.0.2.dist-info/licenses/LICENSE
os_py_lib_cloud-1.0.2.dist-info/METADATA
os_py_lib_cloud-1.0.2.dist-info/WHEEL
os_py_lib_cloud-1.0.2.dist-info/top_level.txt
os_py_lib_cloud-1.0.2.dist-info/RECORD
