Metadata-Version: 2.4
Name: os-py-lib-cloud
Version: 1.0.2
Summary: Unified AWS S3, Azure Blob Storage, and GCP Cloud Storage client for cloud file uploads
Author-email: Oleg Smirnov <oleg.a.smirnov@gmail.com>
License: BSD
Project-URL: Homepage, https://github.com/BestianCode/os.py.lib.cloud
Project-URL: Repository, https://github.com/BestianCode/os.py.lib.cloud
Project-URL: Issues, https://github.com/BestianCode/os.py.lib.cloud/issues
Keywords: aws,s3,azure,blob-storage,gcp,google-cloud-storage,cloud-storage
Classifier: Development Status :: 4 - Beta
Classifier: Intended Audience :: Developers
Classifier: License :: OSI Approved :: BSD License
Classifier: Programming Language :: Python :: 3
Classifier: Programming Language :: Python :: 3.8
Classifier: Programming Language :: Python :: 3.9
Classifier: Programming Language :: Python :: 3.10
Classifier: Programming Language :: Python :: 3.11
Classifier: Programming Language :: Python :: 3.12
Requires-Python: >=3.8
License-File: LICENSE
Requires-Dist: boto3>=1.26.0
Requires-Dist: botocore>=1.29.0
Requires-Dist: azure-storage-blob>=12.19.0
Requires-Dist: azure-core>=1.29.0
Requires-Dist: google-cloud-storage>=2.10.0
Requires-Dist: requests>=2.28.0
Provides-Extra: dev
Requires-Dist: pytest>=7.0; extra == "dev"
Requires-Dist: pytest-cov>=4.0; extra == "dev"
Requires-Dist: black>=23.0; extra == "dev"
Requires-Dist: flake8>=6.0; extra == "dev"
Requires-Dist: mypy>=1.0; extra == "dev"
Dynamic: license-file
